v7e_utils/__init__.py
v7e_utils/agil_connect/__init__.py
v7e_utils/agil_connect/agil_connect.py
v7e_utils/agil_connect/panel_connect.py
v7e_utils/agil_connect/rh_connect.py
v7e_utils/agil_connect/token.py
v7e_utils/agil_connect/token_wrapper.py
v7e_utils/api/__init__.py
v7e_utils/api/apps.py
v7e_utils/api/uls.py
v7e_utils/api/viewsets.py
v7e_utils/apps.py
v7e_utils/data_helper/__init__.py
v7e_utils/data_helper/data_helper.py
v7e_utils/data_helper/error.py
v7e_utils/data_helper/record_batch.py
v7e_utils/data_utils.py
v7e_utils/dataframe_helper/__init__.py
v7e_utils/dataframe_helper/df_helper.py
v7e_utils/dataframe_helper/io.py
v7e_utils/dataframe_helper/utils.py
v7e_utils/date_utils.py
v7e_utils/file_utils.py
v7e_utils/management/__init__.py
v7e_utils/management/commands/__init__.py
v7e_utils/management/commands/get_endpoints.py
v7e_utils/model_utils.py
v7e_utils/report_factory/__init__.py
v7e_utils/report_factory/factory.py
v7e_utils/report_factory/loader.py
v7e_utils/report_factory/publisher.py
v7e_utils/report_factory/report_helper.py
v7e_utils/report_factory/reporter.py
v7e_utils/report_factory/runner.py
v7e_utils/utils/__init__.py
v7e_utils/utils/app_endpoints.py
v7e_utils/utils/config.py
v7e_utils/utils/default_formats.py
v7e_utils/utils/fcm.py
v7e_utils/utils/nextclould.py
v7e_utils/utils/pdf.py
v7e_utils/utils/tests/__init__.py
v7e_utils/utils/tests/test_nextcloud.py
v7e_utils/utils/tests/test_pdf.py
v7e_utils-0.18.7.dist-info/METADATA
v7e_utils-0.18.7.dist-info/WHEEL
v7e_utils-0.18.7.dist-info/RECORD
