Metadata-Version: 2.3
Name: v7e-utils
Version: 0.18.7
Summary: A collection of utility functions for V6E projects
License: MIT
Author: Luis Valverde
Author-email: lvalverde@istmocenter.com
Requires-Python: >=3.9
Classifier: License :: OSI Approved :: MIT License
Classifier: Programming Language :: Python :: 3
Classifier: Programming Language :: Python :: 3.9
Classifier: Programming Language :: Python :: 3.10
Classifier: Programming Language :: Python :: 3.11
Classifier: Programming Language :: Python :: 3.12
Classifier: Programming Language :: Python :: 3.13
Requires-Dist: coverage
Requires-Dist: django
Requires-Dist: djangorestframework
Requires-Dist: drf_spectacular
Requires-Dist: geopy (>=2.2.0)
Requires-Dist: keycloak_django
Requires-Dist: nc_py_api
Requires-Dist: numpy
Requires-Dist: openpyxl (>=3.0.9)
Requires-Dist: pandas
Requires-Dist: pysftp (>=0.2.9)
Requires-Dist: requests
Requires-Dist: tqdm (>=4.62.2)
